LICENSE
README.md
pyproject.toml
setup.cfg
setup.py
taxonerd/__init__.py
taxonerd/abbreviation.py
taxonerd/cli.py
taxonerd/extractor.py
taxonerd/taxonerd.py
taxonerd.egg-info/PKG-INFO
taxonerd.egg-info/SOURCES.txt
taxonerd.egg-info/dependency_links.txt
taxonerd.egg-info/entry_points.txt
taxonerd.egg-info/not-zip-safe
taxonerd.egg-info/requires.txt
taxonerd.egg-info/top_level.txt
taxonerd/linking/__init__.py
taxonerd/linking/candidate_generation.py
taxonerd/linking/file_cache.py
taxonerd/linking/linking.py
taxonerd/linking/linking_utils.py
tests/test_cli.py
tests/test_init.py
tests/test_ner.py