Metadata-Version: 2.1
Name: taxonerd
Version: 1.5.4
Summary: A Python package and CLI tool based on spaCy for detecting mentions of taxonomic entities in text
Home-page: https://github.com/nleguillarme/taxonerd
Author-email: nicolas.leguillarme@univ-grenoble-alpes.fr
License: MIT License
Project-URL: Bug Tracker, https://github.com/nleguillarme/taxonerd/issues
Keywords: spacy,ner,transformers,deep neural networks,ecology,evolution
Classifier: Development Status :: 5 - Production/Stable
Classifier: License :: OSI Approved :: MIT License
Classifier: Programming Language :: Python :: 3.10
Classifier: Environment :: Console
Classifier: Intended Audience :: Developers
Classifier: Intended Audience :: Science/Research
Classifier: Natural Language :: English
Classifier: Topic :: Scientific/Engineering :: Artificial Intelligence
Provides-Extra: cuda11x
Provides-Extra: cuda12x
Provides-Extra: cuda-autodetect
License-File: LICENSE
